LICENSE
README.md
setup.py
sophie/Sophie.automaton
sophie/__init__.py
sophie/__main__.py
sophie/calculus.py
sophie/cmdline.py
sophie/demand.py
sophie/diagnostics.py
sophie/executive.py
sophie/front_end.py
sophie/intermediate.py
sophie/modularity.py
sophie/ontology.py
sophie/primitive.py
sophie/resolution.py
sophie/runtime.py
sophie/scheduler.py
sophie/stacking.py
sophie/syntax.py
sophie/type_evaluator.py
sophie/adapters/__init__.py
sophie/adapters/fs_adapter.py
sophie/adapters/game_adapter.py
sophie/adapters/teletype_adapter.py
sophie/adapters/turtle_adapter.py
sophie/adapters/yarn.py
sophie/sys/2d.sg
sophie/sys/complex.sg
sophie/sys/game.sg
sophie/sys/preamble.sg
sophie/sys/tree.sg
sophie/sys/turtle.sg
sophie_lang.egg-info/PKG-INFO
sophie_lang.egg-info/SOURCES.txt
sophie_lang.egg-info/dependency_links.txt
sophie_lang.egg-info/entry_points.txt
sophie_lang.egg-info/requires.txt
sophie_lang.egg-info/top_level.txt