Metadata-Version: 2.1
Name: sophie-lang
Version: 0.0.7
Summary: A call-by-need strongly-static-duck-typed language named for French mathematician Sophie Germain
Home-page: https://github.com/kjosib/sophie
Author: Ian Kjos
Author-email: kjosib@gmail.com
License: MIT
Platform: UNKNOWN
Classifier: Programming Language :: Python :: 3.9
Classifier: License :: OSI Approved :: MIT License
Classifier: Operating System :: OS Independent
Classifier: Development Status :: 3 - Alpha
Classifier: Intended Audience :: Developers
Classifier: Intended Audience :: Education
Classifier: Topic :: Software Development :: Interpreters
Classifier: Topic :: Software Development :: Compilers
Classifier: Topic :: Education
Classifier: Environment :: Console
Requires-Python: >=3.9
License-File: LICENSE
